cirron/__init__.py
cirron/apple_arm_events.h
cirron/cirron.py
cirron/cirronlib.cpp
cirron/injector.py
cirron/tracer.py
Cirron-0.4.dist-info/METADATA
Cirron-0.4.dist-info/WHEEL
Cirron-0.4.dist-info/top_level.txt
Cirron-0.4.dist-info/RECORD
